clabate/__init__.py
clabate/core.py
clabate/invoke.py
clabate/markup.py
clabate/examples/__init__.py
clabate/examples/basic_examples.py
clabate/examples/comments_examples.py
clabate/examples/file_inclusion_examples.py
clabate/examples/invoke_examples.py
clabate/examples/markup_examples.py
clabate/examples/pygments_examples.py
clabate/examples/run_examples.py
clabate/examples/sequence_examples.py
clabate/extras/__init__.py
clabate/extras/inclusion.py
clabate/extras/pygments.py
clabate/extras/sequence.py
clabate-0.5.0.dist-info/LICENSE
clabate-0.5.0.dist-info/METADATA
clabate-0.5.0.dist-info/WHEEL
clabate-0.5.0.dist-info/top_level.txt
clabate-0.5.0.dist-info/RECORD
